radstar/core/fernet/models.py
radstar/core/fernet/unit.yml
radstar/core/fernet/db.py
radstar/core/fernet/requirements.in
radstar/core/fernet/lib.py
radstar/core/jsonrpc/unit.yml
radstar/core/jsonrpc/lib.py
radstar/core/jsonrpc/web.py
radstar/core/namespaces/models.py
radstar/core/namespaces/unit.yml
radstar/core/namespaces/db.py
radstar/core/namespaces/requirements.in
radstar/core/namespaces/lib.py
radstar/core/namespaces/web.py
radstar/core/celery/unit.yml
radstar/core/celery/run.py
radstar/core/celery/celery_app.py
radstar/core/celery/requirements.in
radstar/core/celery/lib.py
radstar/core/webd/unit.yml
radstar/core/webd/db.py
radstar/core/webd/run.py
radstar/core/webd/requirements.in
radstar/core/webd/lib.py
radstar/core/webd/server/model.py
radstar/core/webd/server/notify.py
radstar/core/webd/server/__init__.py
radstar/core/webd/server/auth.py
radstar/core/webd/server/websocket.py
radstar/core/webd/server/__main__.py
radstar/core/users/models.py
radstar/core/users/unit.yml
radstar/core/users/db.py
radstar/core/users/requirements.in
radstar/core/users/web.py
radstar/rs/__init__.py
radstar/rs/plugins.py
radstar/rs/event.py
radstar/rs/unit.py
radstar/rs/settings.py
radstar/rs/utils.py
radstar/rs/cli/db.py
radstar/rs/cli/__init__.py
radstar/rs/cli/run.py
radstar/rs/cli/deps.py
radstar/rs/cli/setup.py
radstar/rs/cli/configure.py
radstar/rs/cli/python.py
radstar/rs/cli/__main__.py
radstar/rs/db/__init__.py
radstar/rs/db/dbobj.py
radstar/rs/db/funcs.py
radstar/rs/core/unit.yml
radstar/rs/core/requirements.in
radstar/rs/core/project_files/docker-compose.yml.j2
radstar/rs/core/project_files/dot-dockerignore
radstar/rs/core/project_files/Dockerfile.j2
radstar/rs/core/project_files/dot-gitignore.j2
radstar/rs/core/project_files/dot-devcontainer/post-create.sh
radstar/rs/core/project_files/dot-devcontainer/docker-compose.yml.j2
radstar/rs/core/project_files/dot-devcontainer/Dockerfile.j2
radstar/rs/core/project_files/dot-devcontainer/devcontainer.json.j2
radstar-0.17.1.dist-info/entry_points.txt
radstar-0.17.1.dist-info/top_level.txt
radstar-0.17.1.dist-info/METADATA
radstar-0.17.1.dist-info/WHEEL
radstar-0.17.1.dist-info/LICENSE
radstar-0.17.1.dist-info/RECORD
